agentune/__init__.py
agentune/analyze/__init__.py
agentune/analyze/feature/__init__.py
agentune/analyze/feature/base.py
agentune/analyze/feature/compute/__init__.py
agentune/analyze/feature/compute/base.py
agentune/analyze/feature/compute/limits.py
agentune/analyze/feature/compute/universal.py
agentune/analyze/feature/dedup_names.py
agentune/analyze/feature/gen/__init__.py
agentune/analyze/feature/gen/base.py
agentune/analyze/feature/gen/insightful_text_generator/__init__.py
agentune/analyze/feature/gen/insightful_text_generator/dedup/__init__.py
agentune/analyze/feature/gen/insightful_text_generator/dedup/base.py
agentune/analyze/feature/gen/insightful_text_generator/dedup/llm_based_deduplicator.py
agentune/analyze/feature/gen/insightful_text_generator/features.py
agentune/analyze/feature/gen/insightful_text_generator/formatting/__init__.py
agentune/analyze/feature/gen/insightful_text_generator/formatting/base.py
agentune/analyze/feature/gen/insightful_text_generator/formatting/conversation.py
agentune/analyze/feature/gen/insightful_text_generator/insightful_text_generator.py
agentune/analyze/feature/gen/insightful_text_generator/prompts.py
agentune/analyze/feature/gen/insightful_text_generator/query_generator.py
agentune/analyze/feature/gen/insightful_text_generator/sampling/__init__.py
agentune/analyze/feature/gen/insightful_text_generator/sampling/base.py
agentune/analyze/feature/gen/insightful_text_generator/sampling/samplers.py
agentune/analyze/feature/gen/insightful_text_generator/schema.py
agentune/analyze/feature/gen/insightful_text_generator/type_detector.py
agentune/analyze/feature/gen/insightful_text_generator/util.py
agentune/analyze/feature/problem.py
agentune/analyze/feature/select/__init__.py
agentune/analyze/feature/select/base.py
agentune/analyze/feature/select/lightgbm.py
agentune/analyze/feature/select/linear_pairwise.py
agentune/analyze/feature/stats/__init__.py
agentune/analyze/feature/stats/base.py
agentune-0.1.1.dist-info/LICENSE
agentune-0.1.1.dist-info/METADATA
agentune-0.1.1.dist-info/WHEEL
agentune-0.1.1.dist-info/RECORD
