Metadata-Version: 2.3
Name: agentune
Version: 0.1.1
Summary: Analyze AI agents to understand their performance and get improvement suggestions to make them better
License: Apache-2.0
Keywords: agent optimization,AI agent improvement,agent evaluation,customer support,sales agents,conversational agents,AI agents,chatbot evaluation,customer service,customer facing agents
Author: Agentune dev team
Author-email: agentune-dev@sparkbeyond.com
Requires-Python: >=3.12.6,<4.0
Classifier: Development Status :: 4 - Beta
Classifier: Intended Audience :: Developers
Classifier: Intended Audience :: Science/Research
Classifier: Topic :: Scientific/Engineering :: Artificial Intelligence
Classifier: Topic :: Software Development :: Libraries :: Python Modules
Classifier: Programming Language :: Python :: 3
Classifier: Programming Language :: Python :: 3.12
Classifier: Programming Language :: Python :: 3.13
Classifier: Programming Language :: Python :: 3.14
Classifier: License :: OSI Approved :: Apache Software License
Requires-Dist: attrs (>=25.3.0,<26.0.0)
Requires-Dist: cattrs (>=25.3.0,<26.0.0)
Requires-Dist: duckdb (>=1.4.1,<1.5.0)
Requires-Dist: frozendict (>=2.4.6,<3.0.0)
Requires-Dist: httpx[http2] (>=0.28.1,<0.29.0)
Requires-Dist: janus (>=2.0.0,<3.0.0)
Requires-Dist: lightgbm (>=4.6.0,<5.0.0)
Requires-Dist: llama-index-core (>=0.14.7,<0.15.0)
Requires-Dist: llama-index-llms-openai (>=0.6.7,<0.7.0)
Requires-Dist: more-itertools (>=10.7.0,<11.0.0)
Requires-Dist: numpy (>=2.2.4,<3.0.0)
Requires-Dist: polars (>=1.27.1,<2.0.0)
Requires-Dist: pyarrow (>=19.0.1)
Requires-Dist: scikit-learn (>=1.6.1,<2.0.0)
Requires-Dist: scipy (>=1.15.3,<2.0.0)
Requires-Dist: scipy-stubs (>=1.15.3.0,<2.0.0.0)
Project-URL: Documentation, https://github.com/SparkBeyond/agentune/tree/main/
Project-URL: Homepage, https://github.com/SparkBeyond/agentune/tree/main/
Project-URL: Repository, https://github.com/SparkBeyond/agentune
